semantic_admin/__init__.py
semantic_admin/admin.py
semantic_admin/awesomesearch.py
semantic_admin/contrib/__init__.py
semantic_admin/contrib/import_export/__init__.py
semantic_admin/contrib/import_export/admin.py
semantic_admin/contrib/import_export/forms.py
semantic_admin/contrib/import_export/widgets.py
semantic_admin/helpers.py
semantic_admin/static/admin/js/actions.js
semantic_admin/static/admin/js/admin/DateTimeShortcuts.js
semantic_admin/static/admin/js/admin/RelatedObjectLookups.js
semantic_admin/static/admin/js/inlines.js
semantic_admin/static/semantic_admin/django-white.svg
semantic_admin/static/semantic_admin/semantic-admin.css
semantic_admin/static/semantic_admin/unsemantic.css
semantic_admin/templates/admin/actions.html
semantic_admin/templates/admin/auth/user/add_form.html
semantic_admin/templates/admin/base.html
semantic_admin/templates/admin/base_site.html
semantic_admin/templates/admin/change_form.html
semantic_admin/templates/admin/change_list.html
semantic_admin/templates/admin/change_list_results.html
semantic_admin/templates/admin/date_hierarchy.html
semantic_admin/templates/admin/delete_button.html
semantic_admin/templates/admin/delete_confirmation.html
semantic_admin/templates/admin/delete_selected_confirmation.html
semantic_admin/templates/admin/edit_inline/stacked.html
semantic_admin/templates/admin/edit_inline/tabular.html
semantic_admin/templates/admin/filter.html
semantic_admin/templates/admin/import_export/base.html
semantic_admin/templates/admin/import_export/change_list.html
semantic_admin/templates/admin/import_export/change_list_export_item.html
semantic_admin/templates/admin/import_export/change_list_import_item.html
semantic_admin/templates/admin/import_export/export.html
semantic_admin/templates/admin/import_export/export_action_select.html
semantic_admin/templates/admin/import_export/import.html
semantic_admin/templates/admin/import_export/resource_fields_list.html
semantic_admin/templates/admin/includes/fieldset.html
django_semantic_admin-0.6.6.dist-info/LICENSE
django_semantic_admin-0.6.6.dist-info/METADATA
django_semantic_admin-0.6.6.dist-info/WHEEL
django_semantic_admin-0.6.6.dist-info/RECORD
