Metadata-Version: 2.1
Name: django-semantic-admin
Version: 0.6.6
Summary: Django Semantic UI Admin theme
Home-page: https://github.com/globophobe/django-semantic-admin
License: MIT
Keywords: django,admin,theme
Author: Alex
Author-email: globophobe@gmail.com
Requires-Python: >=3.10
Classifier: Development Status :: 4 - Beta
Classifier: Framework :: Django
Classifier: License :: OSI Approved :: MIT License
Classifier: Operating System :: OS Independent
Classifier: Programming Language :: Python :: 3
Classifier: Programming Language :: Python :: 3.10
Classifier: Programming Language :: Python :: 3.11
Classifier: Programming Language :: Python :: 3.12
Provides-Extra: import-export
Requires-Dist: django (>=3.2)
Requires-Dist: django-import-export (<=3.3.9) ; extra == "import-export"
Requires-Dist: django-semantic-forms
Project-URL: Repository, https://github.com/globophobe/django-semantic-admin
